xbox_webapi_ex-1.1.9-py3.6-nspkg.pth
xbox/webapi/__init__.py
xbox/webapi/api/__init__.py
xbox/webapi/api/client.py
xbox/webapi/api/language.py
xbox/webapi/api/provider/__init__.py
xbox/webapi/api/provider/account.py
xbox/webapi/api/provider/achievements.py
xbox/webapi/api/provider/baseprovider.py
xbox/webapi/api/provider/cqs.py
xbox/webapi/api/provider/eds.py
xbox/webapi/api/provider/gameclips.py
xbox/webapi/api/provider/lists.py
xbox/webapi/api/provider/message.py
xbox/webapi/api/provider/people.py
xbox/webapi/api/provider/presence.py
xbox/webapi/api/provider/profile.py
xbox/webapi/api/provider/screenshots.py
xbox/webapi/api/provider/titlehub.py
xbox/webapi/api/provider/usersearch.py
xbox/webapi/api/provider/userstats.py
xbox/webapi/authentication/__init__.py
xbox/webapi/authentication/manager.py
xbox/webapi/authentication/token.py
xbox/webapi/authentication/two_factor.py
xbox/webapi/common/__init__.py
xbox/webapi/common/enum.py
xbox/webapi/common/exceptions.py
xbox/webapi/common/userinfo.py
xbox/webapi/scripts/__init__.py
xbox/webapi/scripts/authenticate.py
xbox/webapi/scripts/browserauth.py
xbox/webapi/scripts/change_gamertag.py
xbox/webapi/scripts/search.py
xbox/webapi/scripts/tui.py
xbox_webapi_ex-1.1.9.dist-info/LICENSE
xbox_webapi_ex-1.1.9.dist-info/METADATA
xbox_webapi_ex-1.1.9.dist-info/WHEEL
xbox_webapi_ex-1.1.9.dist-info/entry_points.txt
xbox_webapi_ex-1.1.9.dist-info/namespace_packages.txt
xbox_webapi_ex-1.1.9.dist-info/top_level.txt
xbox_webapi_ex-1.1.9.dist-info/RECORD
