Metadata-Version: 2.1
Name: xbox-webapi-ex
Version: 1.1.9
Summary: A library to authenticate with Windows Live/Xbox Live and use their API
Home-page: https://github.com/Prouser123/xbox-webapi-python
Author: OpenXbox
Author-email: xbox-webapi-ex@prouser123.me
License: GPL
Keywords: xbox one live api
Platform: UNKNOWN
Classifier: Development Status :: 4 - Beta
Classifier: Intended Audience :: Developers
Classifier: License :: OSI Approved :: GNU General Public License v3 (GPLv3)
Classifier: Topic :: Software Development :: Libraries :: Python Modules
Classifier: Programming Language :: Python :: 3
Classifier: Programming Language :: Python :: 3.5
Classifier: Programming Language :: Python :: 3.6
Classifier: Programming Language :: Python :: 3.7
Provides-Extra: dev
